json_patch_rules/__init__.py
json_patch_rules/__symbols__.py
json_patch_rules/paths.py
tests/__init__.py
tests/test_module.py
python_json_patch_rules-0.3.2.dist-info/LICENSE
python_json_patch_rules-0.3.2.dist-info/METADATA
python_json_patch_rules-0.3.2.dist-info/WHEEL
python_json_patch_rules-0.3.2.dist-info/top_level.txt
python_json_patch_rules-0.3.2.dist-info/RECORD
