Metadata-Version: 2.1
Name: python-json-patch-rules
Version: 0.3.2
Summary: A library to apply JSON patches with rule-based access control.
Home-page: https://github.com/agutoli/python-json-patch-rules
Author: Bruno Agutoli
Author-email: bruno.agutoli@gmail.com
License: MIT
Classifier: Programming Language :: Python :: 3
Classifier: License :: OSI Approved :: MIT License
Classifier: Operating System :: OS Independent
Requires-Python: >=3.6
License-File: LICENSE
Requires-Dist: pydash
